dora_yolo/__init__.py
dora_yolo/main.py
dora_yolo-0.4.1.dist-info/METADATA
dora_yolo-0.4.1.dist-info/WHEEL
dora_yolo-0.4.1.dist-info/entry_points.txt
dora_yolo-0.4.1.dist-info/top_level.txt
dora_yolo-0.4.1.dist-info/RECORD
