Metadata-Version: 2.4
Name: dora-yolo
Version: 0.4.1
Summary: Dora Node for object detection with dora YOLOv8
Author-email: Haixuan Xavier Tao <tao.xavier@outlook.com>, Enzo Le Van <dev@enzo-le-van.fr>
License: MIT
Requires-Python: >=3.8
Requires-Dist: dora-rs>=0.3.9
Requires-Dist: numpy<2.0.0
Requires-Dist: ultralytics>=8.3.24
